nyx_extras/__init__.py
nyx_extras/langchain.py
nyx_extras/utils.py
nyx_extras-0.2.5.dist-info/METADATA
nyx_extras-0.2.5.dist-info/WHEEL
nyx_extras-0.2.5.dist-info/entry_points.txt
nyx_extras-0.2.5.dist-info/RECORD
